pyminder/__init__.py
pyminder/beeminder.py
pyminder/goal.py
pyminder/goal_factory.py
pyminder/pyminder.py
pyminder/python.py
pyminder-1.1.1.dist-info/LICENSE
pyminder-1.1.1.dist-info/METADATA
pyminder-1.1.1.dist-info/WHEEL
pyminder-1.1.1.dist-info/top_level.txt
pyminder-1.1.1.dist-info/RECORD
