Metadata-Version: 2.1
Name: pyminder
Version: 1.1.1
Summary: Beeminder power tools library
Home-page: https://github.com/narthur/pyminder
Author: Nathan Arthur
Author-email: nathan@nathanarthur.com
License: MIT
Platform: UNKNOWN
Classifier: License :: OSI Approved :: MIT License
Classifier: Programming Language :: Python :: 3
Classifier: Programming Language :: Python :: 3.7
Requires-Python: >3.6
Requires-Dist: requests
Requires-Dist: natlibpy
